aws_utility_library_roshinswebapp/__init__.py
aws_utility_library_roshinswebapp/dynamodb_utils.py
aws_utility_library_roshinswebapp/lambda_utils.py
aws_utility_library_roshinswebapp/s3_utils.py
aws_utility_library_roshinswebapp/sns_utils.py
aws_utility_library_roshinswebapp/sqs_utils.py
aws_utility_library_roshinswebapp-1.0.0.dist-info/LICENSE
aws_utility_library_roshinswebapp-1.0.0.dist-info/METADATA
aws_utility_library_roshinswebapp-1.0.0.dist-info/WHEEL
aws_utility_library_roshinswebapp-1.0.0.dist-info/top_level.txt
aws_utility_library_roshinswebapp-1.0.0.dist-info/RECORD
