Metadata-Version: 2.1
Name: aws_utility_library_roshinswebapp
Version: 1.0.0
Summary: A Python library for AWS utilities (Lambda, SNS, SQS, DynamoDB, and S3)
Author-email: Roshin Philip <philip.roshin@gmail.com>
License: MIT License
Requires-Python: >=3.6
License-File: LICENSE
Requires-Dist: boto3<2.0,>=1.20
